setup.py
python_syncope.egg-info/PKG-INFO
python_syncope.egg-info/SOURCES.txt
python_syncope.egg-info/dependency_links.txt
python_syncope.egg-info/not-zip-safe
python_syncope.egg-info/pbr.json
python_syncope.egg-info/requires.txt
python_syncope.egg-info/top_level.txt
syncope/__init__.py