Metadata-Version: 1.1
Name: python-syncope
Version: 0.0.5
Summary: Managing Syncope via rest API
Home-page: http://github.com/dj-wasabi/python-syncope
Author: Werner Dijkerman
Author-email: ikben@werner-dijkerman.nl
License: Apache License 2.0
Download-URL: http://github.com/dj-wasabi/python-syncope
Keywords: syncope
Platform: any
Classifier: Development Status :: 3 - Alpha
Classifier: Operating System :: Unix
Classifier: Programming Language :: Python :: 2.7
